README.rst
setup.py
expr/__init__.py
expr/exceptions.py
expr/expressions.py
expr/operations.py
expr.egg-info/PKG-INFO
expr.egg-info/SOURCES.txt
expr.egg-info/dependency_links.txt
expr.egg-info/requires.txt
expr.egg-info/top_level.txt