Metadata-Version: 1.0
Name: expr
Version: 0.0.1f
Summary: Draw little expression graphs; made to be hacked on.
Home-page: https://github.com/bmcorser/expr
Author: bmcorser
Author-email: bmcorser@gmail.com
License: UNKNOWN
Platform: UNKNOWN
